trafficintelligence/__init__.py
trafficintelligence/base.py
trafficintelligence/cvutils.py
trafficintelligence/events.py
trafficintelligence/indicators.py
trafficintelligence/metadata.py
trafficintelligence/ml.py
trafficintelligence/moving.py
trafficintelligence/objectsmoothing.py
trafficintelligence/pavement.py
trafficintelligence/poly_utils.py
trafficintelligence/prediction.py
trafficintelligence/processing.py
trafficintelligence/sensors.py
trafficintelligence/storage.py
trafficintelligence/sumo.py
trafficintelligence/traffic_engineering.py
trafficintelligence/ubc_utils.py
trafficintelligence/utils.py
trafficintelligence-0.2.6.dist-info/LICENSE
trafficintelligence-0.2.6.dist-info/METADATA
trafficintelligence-0.2.6.dist-info/WHEEL
trafficintelligence-0.2.6.dist-info/top_level.txt
trafficintelligence-0.2.6.dist-info/RECORD
