Metadata-Version: 2.1
Name: trafficintelligence
Version: 0.2.6
Summary: Python modules of the Traffic Intelligence project
Home-page: https://bitbucket.org/Nicolas/trafficintelligence
Author: Nicolas Saunier
Author-email: nicolas.saunier@polymtl.ca
License: MIT License
Platform: UNKNOWN
Classifier: Programming Language :: Python :: 3
Classifier: License :: OSI Approved :: MIT License
Classifier: Operating System :: OS Independent
